ultrawave/__init__.py
ultrawave/controller.py
ultrawave-1.0.1.dist-info/METADATA
ultrawave-1.0.1.dist-info/WHEEL
ultrawave-1.0.1.dist-info/top_level.txt
ultrawave-1.0.1.dist-info/RECORD
