Metadata-Version: 2.1
Name: ultrawave
Version: 1.0.1
Summary: Lib for read UHF Scanner
Home-page: https://github.com/ipungg-junior/ultrawave
Author: Muhammad Thoyfur
Author-email: ipungg.id@gmail.com
Requires-Python: >=3.7
